{
  "last_fetch": "2026-04-01T09:20:33.504Z",
  "total_fetched": 192864,
  "source_stats": {
    "CoinDesk": {
      "count": 25,
      "error": null,
      "ms": 498,
      "updated_at": "2026-04-01T09:20:33.504Z"
    },
    "CoinTelegraph": {
      "count": 30,
      "error": null,
      "ms": 185,
      "updated_at": "2026-04-01T09:20:33.504Z"
    },
    "Decrypt": {
      "count": 34,
      "error": null,
      "ms": 122,
      "updated_at": "2026-04-01T09:20:33.504Z"
    },
    "The Block": {
      "count": 19,
      "error": null,
      "ms": 146,
      "updated_at": "2026-04-01T09:20:33.504Z"
    },
    "Bitcoin Magazine": {
      "count": 10,
      "error": null,
      "ms": 424,
      "updated_at": "2026-04-01T09:20:33.504Z"
    },
    "BeInCrypto": {
      "count": 12,
      "error": null,
      "ms": 260,
      "updated_at": "2026-04-01T09:20:33.504Z"
    },
    "CryptoSlate": {
      "count": 10,
      "error": null,
      "ms": 1002,
      "updated_at": "2026-04-01T09:20:33.504Z"
    },
    "CryptoBriefing": {
      "count": 30,
      "error": null,
      "ms": 387,
      "updated_at": "2026-04-01T09:20:33.504Z"
    },
    "NewsBTC": {
      "count": 10,
      "error": null,
      "ms": 389,
      "updated_at": "2026-04-01T09:20:33.504Z"
    },
    "U.Today": {
      "count": 94,
      "error": null,
      "ms": 432,
      "updated_at": "2026-04-01T09:20:33.504Z"
    },
    "AMBCrypto": {
      "count": 16,
      "error": null,
      "ms": 188,
      "updated_at": "2026-04-01T09:20:33.504Z"
    },
    "CryptoNews": {
      "count": 20,
      "error": null,
      "ms": 843,
      "updated_at": "2026-04-01T09:20:33.504Z"
    },
    "ZyCrypto": {
      "count": 14,
      "error": null,
      "ms": 638,
      "updated_at": "2026-04-01T09:20:33.504Z"
    },
    "BitcoinNews": {
      "count": 8,
      "error": null,
      "ms": 173,
      "updated_at": "2026-04-01T09:20:33.504Z"
    },
    "CoinJournal": {
      "count": 9,
      "error": null,
      "ms": 386,
      "updated_at": "2026-04-01T09:20:33.504Z"
    },
    "DailyHodl": {
      "count": 10,
      "error": null,
      "ms": 307,
      "updated_at": "2026-04-01T09:20:33.504Z"
    },
    "CryptoGlobe": {
      "count": 0,
      "error": null,
      "ms": 616,
      "updated_at": "2026-04-01T09:20:33.504Z"
    },
    "Blockworks": {
      "count": 50,
      "error": null,
      "ms": 600,
      "updated_at": "2026-04-01T09:20:33.504Z"
    },
    "The Defiant": {
      "count": 100,
      "error": null,
      "ms": 380,
      "updated_at": "2026-04-01T09:20:33.504Z"
    },
    "Unchained": {
      "count": 10,
      "error": null,
      "ms": 869,
      "updated_at": "2026-04-01T09:20:33.504Z"
    },
    "CoinTelegraph Markets": {
      "count": 30,
      "error": null,
      "ms": 122,
      "updated_at": "2026-04-01T09:20:33.504Z"
    },
    "CoinTelegraph Regulation": {
      "count": 30,
      "error": null,
      "ms": 143,
      "updated_at": "2026-04-01T09:20:33.504Z"
    },
    "CoinTelegraph Bitcoin": {
      "count": 30,
      "error": null,
      "ms": 160,
      "updated_at": "2026-04-01T09:20:33.504Z"
    },
    "CoinPost": {
      "count": 16,
      "error": null,
      "ms": 1872,
      "updated_at": "2026-04-01T09:20:33.504Z"
    },
    "CoinDesk Japan": {
      "count": 10,
      "error": null,
      "ms": 1770,
      "updated_at": "2026-04-01T09:20:33.504Z"
    },
    "Minkabu Crypto": {
      "count": 0,
      "error": "fetch failed",
      "ms": 236,
      "updated_at": "2026-04-01T09:20:33.504Z"
    },
    "CryptoTimes": {
      "count": 20,
      "error": null,
      "ms": 532,
      "updated_at": "2026-04-01T09:20:33.504Z"
    },
    "HashHub Research": {
      "count": 0,
      "error": "HTTP 404",
      "ms": 865,
      "updated_at": "2026-04-01T09:20:33.504Z"
    },
    "CoinOtaku": {
      "count": 10,
      "error": null,
      "ms": 2085,
      "updated_at": "2026-04-01T09:20:33.504Z"
    },
    "BitcoinNews Japan": {
      "count": 0,
      "error": "fetch failed",
      "ms": 423,
      "updated_at": "2026-04-01T09:20:33.504Z"
    }
  }
}