{
  "last_fetch": "2026-03-25T12:50:41.975Z",
  "total_fetched": 67348,
  "source_stats": {
    "CoinDesk": {
      "count": 25,
      "error": null,
      "ms": 615,
      "updated_at": "2026-03-25T12:50:41.975Z"
    },
    "CoinTelegraph": {
      "count": 30,
      "error": null,
      "ms": 97,
      "updated_at": "2026-03-25T12:50:41.975Z"
    },
    "Decrypt": {
      "count": 55,
      "error": null,
      "ms": 100,
      "updated_at": "2026-03-25T12:50:41.975Z"
    },
    "The Block": {
      "count": 20,
      "error": null,
      "ms": 102,
      "updated_at": "2026-03-25T12:50:41.975Z"
    },
    "Bitcoin Magazine": {
      "count": 10,
      "error": null,
      "ms": 452,
      "updated_at": "2026-03-25T12:50:41.975Z"
    },
    "BeInCrypto": {
      "count": 12,
      "error": null,
      "ms": 240,
      "updated_at": "2026-03-25T12:50:41.975Z"
    },
    "CryptoSlate": {
      "count": 10,
      "error": null,
      "ms": 763,
      "updated_at": "2026-03-25T12:50:41.975Z"
    },
    "CryptoBriefing": {
      "count": 30,
      "error": null,
      "ms": 428,
      "updated_at": "2026-03-25T12:50:41.975Z"
    },
    "NewsBTC": {
      "count": 10,
      "error": null,
      "ms": 404,
      "updated_at": "2026-03-25T12:50:41.975Z"
    },
    "U.Today": {
      "count": 96,
      "error": null,
      "ms": 409,
      "updated_at": "2026-03-25T12:50:41.975Z"
    },
    "AMBCrypto": {
      "count": 16,
      "error": null,
      "ms": 47,
      "updated_at": "2026-03-25T12:50:41.975Z"
    },
    "CryptoNews": {
      "count": 20,
      "error": null,
      "ms": 959,
      "updated_at": "2026-03-25T12:50:41.975Z"
    },
    "ZyCrypto": {
      "count": 14,
      "error": null,
      "ms": 246,
      "updated_at": "2026-03-25T12:50:41.975Z"
    },
    "BitcoinNews": {
      "count": 8,
      "error": null,
      "ms": 100,
      "updated_at": "2026-03-25T12:50:41.975Z"
    },
    "CoinJournal": {
      "count": 9,
      "error": null,
      "ms": 379,
      "updated_at": "2026-03-25T12:50:41.975Z"
    },
    "DailyHodl": {
      "count": 10,
      "error": null,
      "ms": 305,
      "updated_at": "2026-03-25T12:50:41.975Z"
    },
    "CryptoGlobe": {
      "count": 0,
      "error": null,
      "ms": 542,
      "updated_at": "2026-03-25T12:50:41.975Z"
    },
    "Blockworks": {
      "count": 50,
      "error": null,
      "ms": 741,
      "updated_at": "2026-03-25T12:50:41.975Z"
    },
    "The Defiant": {
      "count": 100,
      "error": null,
      "ms": 419,
      "updated_at": "2026-03-25T12:50:41.975Z"
    },
    "Unchained": {
      "count": 10,
      "error": null,
      "ms": 1253,
      "updated_at": "2026-03-25T12:50:41.975Z"
    },
    "CoinTelegraph Markets": {
      "count": 30,
      "error": null,
      "ms": 929,
      "updated_at": "2026-03-25T12:50:41.975Z"
    },
    "CoinTelegraph Regulation": {
      "count": 30,
      "error": null,
      "ms": 146,
      "updated_at": "2026-03-25T12:50:41.975Z"
    },
    "CoinTelegraph Bitcoin": {
      "count": 30,
      "error": null,
      "ms": 74,
      "updated_at": "2026-03-25T12:50:41.975Z"
    },
    "CoinPost": {
      "count": 16,
      "error": null,
      "ms": 1659,
      "updated_at": "2026-03-25T12:50:41.975Z"
    },
    "CoinDesk Japan": {
      "count": 10,
      "error": null,
      "ms": 1262,
      "updated_at": "2026-03-25T12:50:41.975Z"
    },
    "Minkabu Crypto": {
      "count": 0,
      "error": "fetch failed",
      "ms": 144,
      "updated_at": "2026-03-25T12:50:41.975Z"
    },
    "CryptoTimes": {
      "count": 20,
      "error": null,
      "ms": 439,
      "updated_at": "2026-03-25T12:50:41.975Z"
    },
    "HashHub Research": {
      "count": 0,
      "error": "HTTP 404",
      "ms": 542,
      "updated_at": "2026-03-25T12:50:41.975Z"
    },
    "CoinOtaku": {
      "count": 10,
      "error": null,
      "ms": 1934,
      "updated_at": "2026-03-25T12:50:41.975Z"
    },
    "BitcoinNews Japan": {
      "count": 0,
      "error": "fetch failed",
      "ms": 290,
      "updated_at": "2026-03-25T12:50:41.975Z"
    }
  }
}