{
  "last_fetch": "2026-04-03T22:50:36.976Z",
  "total_fetched": 242450,
  "source_stats": {
    "CoinDesk": {
      "count": 25,
      "error": null,
      "ms": 402,
      "updated_at": "2026-04-03T22:50:36.976Z"
    },
    "CoinTelegraph": {
      "count": 30,
      "error": null,
      "ms": 183,
      "updated_at": "2026-04-03T22:50:36.976Z"
    },
    "Decrypt": {
      "count": 37,
      "error": null,
      "ms": 118,
      "updated_at": "2026-04-03T22:50:36.976Z"
    },
    "The Block": {
      "count": 20,
      "error": null,
      "ms": 123,
      "updated_at": "2026-04-03T22:50:36.976Z"
    },
    "Bitcoin Magazine": {
      "count": 10,
      "error": null,
      "ms": 318,
      "updated_at": "2026-04-03T22:50:36.976Z"
    },
    "BeInCrypto": {
      "count": 12,
      "error": null,
      "ms": 199,
      "updated_at": "2026-04-03T22:50:36.976Z"
    },
    "CryptoSlate": {
      "count": 10,
      "error": null,
      "ms": 764,
      "updated_at": "2026-04-03T22:50:36.976Z"
    },
    "CryptoBriefing": {
      "count": 30,
      "error": null,
      "ms": 537,
      "updated_at": "2026-04-03T22:50:36.976Z"
    },
    "NewsBTC": {
      "count": 10,
      "error": null,
      "ms": 216,
      "updated_at": "2026-04-03T22:50:36.976Z"
    },
    "U.Today": {
      "count": 91,
      "error": null,
      "ms": 281,
      "updated_at": "2026-04-03T22:50:36.976Z"
    },
    "AMBCrypto": {
      "count": 16,
      "error": null,
      "ms": 64,
      "updated_at": "2026-04-03T22:50:36.976Z"
    },
    "CryptoNews": {
      "count": 20,
      "error": null,
      "ms": 839,
      "updated_at": "2026-04-03T22:50:36.976Z"
    },
    "ZyCrypto": {
      "count": 14,
      "error": null,
      "ms": 424,
      "updated_at": "2026-04-03T22:50:36.976Z"
    },
    "BitcoinNews": {
      "count": 8,
      "error": null,
      "ms": 209,
      "updated_at": "2026-04-03T22:50:36.976Z"
    },
    "CoinJournal": {
      "count": 9,
      "error": null,
      "ms": 332,
      "updated_at": "2026-04-03T22:50:36.976Z"
    },
    "DailyHodl": {
      "count": 10,
      "error": null,
      "ms": 267,
      "updated_at": "2026-04-03T22:50:36.976Z"
    },
    "CryptoGlobe": {
      "count": 0,
      "error": null,
      "ms": 644,
      "updated_at": "2026-04-03T22:50:36.976Z"
    },
    "Blockworks": {
      "count": 50,
      "error": null,
      "ms": 571,
      "updated_at": "2026-04-03T22:50:36.976Z"
    },
    "The Defiant": {
      "count": 100,
      "error": null,
      "ms": 407,
      "updated_at": "2026-04-03T22:50:36.976Z"
    },
    "Unchained": {
      "count": 10,
      "error": null,
      "ms": 6090,
      "updated_at": "2026-04-03T22:50:36.976Z"
    },
    "CoinTelegraph Markets": {
      "count": 30,
      "error": null,
      "ms": 233,
      "updated_at": "2026-04-03T22:50:36.976Z"
    },
    "CoinTelegraph Regulation": {
      "count": 30,
      "error": null,
      "ms": 137,
      "updated_at": "2026-04-03T22:50:36.976Z"
    },
    "CoinTelegraph Bitcoin": {
      "count": 30,
      "error": null,
      "ms": 128,
      "updated_at": "2026-04-03T22:50:36.976Z"
    },
    "CoinPost": {
      "count": 16,
      "error": null,
      "ms": 1867,
      "updated_at": "2026-04-03T22:50:36.976Z"
    },
    "CoinDesk Japan": {
      "count": 10,
      "error": null,
      "ms": 1398,
      "updated_at": "2026-04-03T22:50:36.976Z"
    },
    "Minkabu Crypto": {
      "count": 0,
      "error": "fetch failed",
      "ms": 164,
      "updated_at": "2026-04-03T22:50:36.976Z"
    },
    "CryptoTimes": {
      "count": 20,
      "error": null,
      "ms": 553,
      "updated_at": "2026-04-03T22:50:36.976Z"
    },
    "HashHub Research": {
      "count": 0,
      "error": "HTTP 404",
      "ms": 690,
      "updated_at": "2026-04-03T22:50:36.976Z"
    },
    "CoinOtaku": {
      "count": 10,
      "error": null,
      "ms": 2082,
      "updated_at": "2026-04-03T22:50:36.976Z"
    },
    "BitcoinNews Japan": {
      "count": 0,
      "error": "fetch failed",
      "ms": 301,
      "updated_at": "2026-04-03T22:50:36.976Z"
    }
  }
}