{
  "last_fetch": "2026-04-14T22:59:38.326Z",
  "total_fetched": 474024,
  "source_stats": {
    "CoinDesk": {
      "count": 25,
      "error": null,
      "ms": 345,
      "updated_at": "2026-04-14T22:59:38.326Z"
    },
    "CoinTelegraph": {
      "count": 30,
      "error": null,
      "ms": 84,
      "updated_at": "2026-04-14T22:59:38.326Z"
    },
    "Decrypt": {
      "count": 57,
      "error": null,
      "ms": 70,
      "updated_at": "2026-04-14T22:59:38.326Z"
    },
    "The Block": {
      "count": 20,
      "error": null,
      "ms": 71,
      "updated_at": "2026-04-14T22:59:38.326Z"
    },
    "Bitcoin Magazine": {
      "count": 10,
      "error": null,
      "ms": 344,
      "updated_at": "2026-04-14T22:59:38.326Z"
    },
    "BeInCrypto": {
      "count": 12,
      "error": null,
      "ms": 236,
      "updated_at": "2026-04-14T22:59:38.326Z"
    },
    "CryptoSlate": {
      "count": 10,
      "error": null,
      "ms": 944,
      "updated_at": "2026-04-14T22:59:38.326Z"
    },
    "CryptoBriefing": {
      "count": 30,
      "error": null,
      "ms": 223,
      "updated_at": "2026-04-14T22:59:38.326Z"
    },
    "NewsBTC": {
      "count": 10,
      "error": null,
      "ms": 293,
      "updated_at": "2026-04-14T22:59:38.326Z"
    },
    "U.Today": {
      "count": 95,
      "error": null,
      "ms": 299,
      "updated_at": "2026-04-14T22:59:38.326Z"
    },
    "AMBCrypto": {
      "count": 16,
      "error": null,
      "ms": 120,
      "updated_at": "2026-04-14T22:59:38.326Z"
    },
    "CryptoNews": {
      "count": 20,
      "error": null,
      "ms": 765,
      "updated_at": "2026-04-14T22:59:38.326Z"
    },
    "ZyCrypto": {
      "count": 0,
      "error": null,
      "ms": 346,
      "updated_at": "2026-04-14T22:59:38.326Z"
    },
    "BitcoinNews": {
      "count": 8,
      "error": null,
      "ms": 119,
      "updated_at": "2026-04-14T22:59:38.326Z"
    },
    "CoinJournal": {
      "count": 9,
      "error": null,
      "ms": 269,
      "updated_at": "2026-04-14T22:59:38.326Z"
    },
    "DailyHodl": {
      "count": 10,
      "error": null,
      "ms": 217,
      "updated_at": "2026-04-14T22:59:38.326Z"
    },
    "CryptoGlobe": {
      "count": 0,
      "error": null,
      "ms": 756,
      "updated_at": "2026-04-14T22:59:38.326Z"
    },
    "Blockworks": {
      "count": 50,
      "error": null,
      "ms": 522,
      "updated_at": "2026-04-14T22:59:38.326Z"
    },
    "The Defiant": {
      "count": 100,
      "error": null,
      "ms": 418,
      "updated_at": "2026-04-14T22:59:38.326Z"
    },
    "Unchained": {
      "count": 10,
      "error": null,
      "ms": 953,
      "updated_at": "2026-04-14T22:59:38.326Z"
    },
    "CoinTelegraph Markets": {
      "count": 30,
      "error": null,
      "ms": 99,
      "updated_at": "2026-04-14T22:59:38.326Z"
    },
    "CoinTelegraph Regulation": {
      "count": 30,
      "error": null,
      "ms": 411,
      "updated_at": "2026-04-14T22:59:38.326Z"
    },
    "CoinTelegraph Bitcoin": {
      "count": 30,
      "error": null,
      "ms": 66,
      "updated_at": "2026-04-14T22:59:38.326Z"
    },
    "CoinPost": {
      "count": 16,
      "error": null,
      "ms": 1828,
      "updated_at": "2026-04-14T22:59:38.326Z"
    },
    "CoinDesk Japan": {
      "count": 10,
      "error": null,
      "ms": 208,
      "updated_at": "2026-04-14T22:59:38.326Z"
    },
    "Minkabu Crypto": {
      "count": 0,
      "error": "fetch failed",
      "ms": 197,
      "updated_at": "2026-04-14T22:59:38.326Z"
    },
    "CryptoTimes": {
      "count": 20,
      "error": null,
      "ms": 339,
      "updated_at": "2026-04-14T22:59:38.326Z"
    },
    "HashHub Research": {
      "count": 0,
      "error": "HTTP 404",
      "ms": 568,
      "updated_at": "2026-04-14T22:59:38.326Z"
    },
    "CoinOtaku": {
      "count": 10,
      "error": null,
      "ms": 2392,
      "updated_at": "2026-04-14T22:59:38.326Z"
    },
    "BitcoinNews Japan": {
      "count": 0,
      "error": "fetch failed",
      "ms": 102,
      "updated_at": "2026-04-14T22:59:38.326Z"
    }
  }
}