[
  {
    "coin_id": "avalanche-2",
    "captured_at": "2026-03-27T08:40:34.606Z",
    "price_jpy": 1434.97,
    "price_usd": 8.98,
    "change_24h": -4.229731487882016,
    "change_7d": 0,
    "market_cap_jpy": 621123198728.9979,
    "volume_24h_jpy": 41895916568.79358
  },
  {
    "coin_id": "binancecoin",
    "captured_at": "2026-03-27T08:40:34.606Z",
    "price_jpy": 99156,
    "price_usd": 620.2,
    "change_24h": -1.7123076192277586,
    "change_7d": 0,
    "market_cap_jpy": 13546528538453.229,
    "volume_24h_jpy": 143913608353.96628
  },
  {
    "coin_id": "bitcoin",
    "captured_at": "2026-03-27T08:40:34.606Z",
    "price_jpy": 10813663,
    "price_usd": 67638,
    "change_24h": -2.940868056734296,
    "change_7d": 0,
    "market_cap_jpy": 216516118708730.8,
    "volume_24h_jpy": 7790230792059.164
  },
  {
    "coin_id": "cardano",
    "captured_at": "2026-03-27T08:40:34.606Z",
    "price_jpy": 40.29,
    "price_usd": 0.251992,
    "change_24h": -2.937779875059809,
    "change_7d": 0,
    "market_cap_jpy": 1486030764806.5034,
    "volume_24h_jpy": 73427241155.93593
  },
  {
    "coin_id": "chainlink",
    "captured_at": "2026-03-27T08:40:34.606Z",
    "price_jpy": 1410.18,
    "price_usd": 8.82,
    "change_24h": -2.4804267890486806,
    "change_7d": 0,
    "market_cap_jpy": 998991000432.3643,
    "volume_24h_jpy": 59409592578.69925
  },
  {
    "coin_id": "dogecoin",
    "captured_at": "2026-03-27T08:40:34.606Z",
    "price_jpy": 14.66,
    "price_usd": 0.091683,
    "change_24h": -0.3563119072139022,
    "change_7d": 0,
    "market_cap_jpy": 2252430171876.1543,
    "volume_24h_jpy": 162095734583.00595
  },
  {
    "coin_id": "ethereum",
    "captured_at": "2026-03-27T08:40:34.606Z",
    "price_jpy": 325693,
    "price_usd": 2037.15,
    "change_24h": -3.4337703596341447,
    "change_7d": 0,
    "market_cap_jpy": 39355912496223.21,
    "volume_24h_jpy": 2928798281893.1855
  },
  {
    "coin_id": "litecoin",
    "captured_at": "2026-03-27T08:40:34.606Z",
    "price_jpy": 8734.52,
    "price_usd": 54.63,
    "change_24h": -0.6179727928988777,
    "change_7d": 0,
    "market_cap_jpy": 672656279220.7275,
    "volume_24h_jpy": 60579549090.545204
  },
  {
    "coin_id": "matic-network",
    "captured_at": "2026-03-27T08:40:34.606Z",
    "price_jpy": 0,
    "price_usd": 0,
    "change_24h": 0,
    "change_7d": 0,
    "market_cap_jpy": 0,
    "volume_24h_jpy": 0
  },
  {
    "coin_id": "near",
    "captured_at": "2026-03-27T08:40:34.606Z",
    "price_jpy": 195.97,
    "price_usd": 1.23,
    "change_24h": 0.07207131031718482,
    "change_7d": 0,
    "market_cap_jpy": 253848744192.67902,
    "volume_24h_jpy": 26611904099.910255
  },
  {
    "coin_id": "polkadot",
    "captured_at": "2026-03-27T08:40:34.606Z",
    "price_jpy": 209.98,
    "price_usd": 1.31,
    "change_24h": -0.22001434393089891,
    "change_7d": 0,
    "market_cap_jpy": 353349900695.8968,
    "volume_24h_jpy": 29439023549.8474
  },
  {
    "coin_id": "ripple",
    "captured_at": "2026-03-27T08:40:34.606Z",
    "price_jpy": 215.56,
    "price_usd": 1.35,
    "change_24h": -2.1870331321925,
    "change_7d": 0,
    "market_cap_jpy": 13229523698220.035,
    "volume_24h_jpy": 407666422611.8963
  },
  {
    "coin_id": "shiba-inu",
    "captured_at": "2026-03-27T08:40:34.606Z",
    "price_jpy": 0.00093792,
    "price_usd": 0.00000587,
    "change_24h": -1.0496860867131907,
    "change_7d": 0,
    "market_cap_jpy": 553384945463.9679,
    "volume_24h_jpy": 15436580923.359972
  },
  {
    "coin_id": "solana",
    "captured_at": "2026-03-27T08:40:34.606Z",
    "price_jpy": 13604.65,
    "price_usd": 85.09,
    "change_24h": -3.8412394356346935,
    "change_7d": 0,
    "market_cap_jpy": 7807213706144.229,
    "volume_24h_jpy": 603629943640.289
  },
  {
    "coin_id": "staked-ether",
    "captured_at": "2026-03-27T08:40:34.606Z",
    "price_jpy": 327196,
    "price_usd": 2046.55,
    "change_24h": -3.0091808672086566,
    "change_7d": 0,
    "market_cap_jpy": 3001483361713.912,
    "volume_24h_jpy": 1734226779.7686818
  },
  {
    "coin_id": "tether",
    "captured_at": "2026-03-27T08:40:34.606Z",
    "price_jpy": 159.78,
    "price_usd": 0.999386,
    "change_24h": 0.22877724540093683,
    "change_7d": 0,
    "market_cap_jpy": 29434454975305,
    "volume_24h_jpy": 12054880519719.23
  },
  {
    "coin_id": "tron",
    "captured_at": "2026-03-27T08:40:34.606Z",
    "price_jpy": 50.59,
    "price_usd": 0.316446,
    "change_24h": 0.8023959501559307,
    "change_7d": 0,
    "market_cap_jpy": 4794311938370.098,
    "volume_24h_jpy": 90925177459.18942
  },
  {
    "coin_id": "uniswap",
    "captured_at": "2026-03-27T08:40:34.606Z",
    "price_jpy": 555.76,
    "price_usd": 3.48,
    "change_24h": -2.954554253608568,
    "change_7d": 0,
    "market_cap_jpy": 352453182793.7492,
    "volume_24h_jpy": 27561730500.3177
  },
  {
    "coin_id": "usd-coin",
    "captured_at": "2026-03-27T08:40:34.606Z",
    "price_jpy": 159.85,
    "price_usd": 0.999833,
    "change_24h": 0.24549536814966952,
    "change_7d": 0,
    "market_cap_jpy": 12462764921999.098,
    "volume_24h_jpy": 1241823169308.982
  },
  {
    "coin_id": "wrapped-bitcoin",
    "captured_at": "2026-03-27T08:40:34.606Z",
    "price_jpy": 10802410,
    "price_usd": 67567,
    "change_24h": -2.759589923880886,
    "change_7d": 0,
    "market_cap_jpy": 1296219944663.4478,
    "volume_24h_jpy": 33585437108.04357
  }
]