[
  {
    "coin_id": "avalanche-2",
    "captured_at": "2026-04-02T07:40:35.838Z",
    "price_jpy": 1392.27,
    "price_usd": 8.72,
    "change_24h": -6.266691634973992,
    "change_7d": 0,
    "market_cap_jpy": 600865847504.0591,
    "volume_24h_jpy": 47114717947.53087
  },
  {
    "coin_id": "binancecoin",
    "captured_at": "2026-04-02T07:40:35.838Z",
    "price_jpy": 94517,
    "price_usd": 592.01,
    "change_24h": -3.321948608907614,
    "change_7d": 0,
    "market_cap_jpy": 12885578422432.71,
    "volume_24h_jpy": 172551970304.99182
  },
  {
    "coin_id": "bitcoin",
    "captured_at": "2026-04-02T07:40:35.838Z",
    "price_jpy": 10665556,
    "price_usd": 66805,
    "change_24h": -2.188621915124491,
    "change_7d": 0,
    "market_cap_jpy": 213397946115885.44,
    "volume_24h_jpy": 6898499617058.97
  },
  {
    "coin_id": "cardano",
    "captured_at": "2026-04-02T07:40:35.838Z",
    "price_jpy": 38.04,
    "price_usd": 0.238295,
    "change_24h": -4.429427305192341,
    "change_7d": 0,
    "market_cap_jpy": 1401995311134.625,
    "volume_24h_jpy": 89673999091.97005
  },
  {
    "coin_id": "chainlink",
    "captured_at": "2026-04-02T07:40:35.838Z",
    "price_jpy": 1365.49,
    "price_usd": 8.55,
    "change_24h": -5.0436984319910865,
    "change_7d": 0,
    "market_cap_jpy": 966858757144.8572,
    "volume_24h_jpy": 61836490109.647644
  },
  {
    "coin_id": "dogecoin",
    "captured_at": "2026-04-02T07:40:35.838Z",
    "price_jpy": 14.39,
    "price_usd": 0.090107,
    "change_24h": -3.215521574106972,
    "change_7d": 0,
    "market_cap_jpy": 2210282460595.5317,
    "volume_24h_jpy": 179719483309.6084
  },
  {
    "coin_id": "ethereum",
    "captured_at": "2026-04-02T07:40:35.838Z",
    "price_jpy": 327550,
    "price_usd": 2051.64,
    "change_24h": -3.268569940416962,
    "change_7d": 0,
    "market_cap_jpy": 39540126982049.46,
    "volume_24h_jpy": 3316180398742.0405
  },
  {
    "coin_id": "litecoin",
    "captured_at": "2026-04-02T07:40:35.838Z",
    "price_jpy": 8382.35,
    "price_usd": 52.5,
    "change_24h": -2.8200313138274704,
    "change_7d": 0,
    "market_cap_jpy": 645696086274.7821,
    "volume_24h_jpy": 62402850614.86851
  },
  {
    "coin_id": "matic-network",
    "captured_at": "2026-04-02T07:40:35.838Z",
    "price_jpy": 0,
    "price_usd": 0,
    "change_24h": 0,
    "change_7d": 0,
    "market_cap_jpy": 0,
    "volume_24h_jpy": 0
  },
  {
    "coin_id": "near",
    "captured_at": "2026-04-02T07:40:35.838Z",
    "price_jpy": 185.41,
    "price_usd": 1.16,
    "change_24h": -4.087190454763662,
    "change_7d": 0,
    "market_cap_jpy": 239351774564.17902,
    "volume_24h_jpy": 29602027605.597282
  },
  {
    "coin_id": "polkadot",
    "captured_at": "2026-04-02T07:40:35.838Z",
    "price_jpy": 195.27,
    "price_usd": 1.22,
    "change_24h": -4.469442274046544,
    "change_7d": 0,
    "market_cap_jpy": 327529126555.3092,
    "volume_24h_jpy": 18220120973.797615
  },
  {
    "coin_id": "ripple",
    "captured_at": "2026-04-02T07:40:35.838Z",
    "price_jpy": 210.32,
    "price_usd": 1.32,
    "change_24h": -2.4639216866542113,
    "change_7d": 0,
    "market_cap_jpy": 12911858347946.227,
    "volume_24h_jpy": 345020521988.8591
  },
  {
    "coin_id": "shiba-inu",
    "captured_at": "2026-04-02T07:40:35.838Z",
    "price_jpy": 0.00093018,
    "price_usd": 0.00000583,
    "change_24h": -2.263236201239746,
    "change_7d": 0,
    "market_cap_jpy": 547964268542.5391,
    "volume_24h_jpy": 20359905175.864384
  },
  {
    "coin_id": "solana",
    "captured_at": "2026-04-02T07:40:35.838Z",
    "price_jpy": 12682.71,
    "price_usd": 79.45,
    "change_24h": -4.854642432289469,
    "change_7d": 0,
    "market_cap_jpy": 7264144801724.344,
    "volume_24h_jpy": 858967500667.7207
  },
  {
    "coin_id": "staked-ether",
    "captured_at": "2026-04-02T07:40:35.838Z",
    "price_jpy": 327352,
    "price_usd": 2050.4,
    "change_24h": -3.320619512612432,
    "change_7d": 0,
    "market_cap_jpy": 3025278287840.4727,
    "volume_24h_jpy": 2181037738.0220594
  },
  {
    "coin_id": "tether",
    "captured_at": "2026-04-02T07:40:35.838Z",
    "price_jpy": 159.63,
    "price_usd": 0.999854,
    "change_24h": 0.8306161582584081,
    "change_7d": 0,
    "market_cap_jpy": 29397960948749.42,
    "volume_24h_jpy": 11848296498080.092
  },
  {
    "coin_id": "tron",
    "captured_at": "2026-04-02T07:40:35.838Z",
    "price_jpy": 50.4,
    "price_usd": 0.315705,
    "change_24h": 0.8997704457661401,
    "change_7d": 0,
    "market_cap_jpy": 4775384729339.433,
    "volume_24h_jpy": 141992557640.9802
  },
  {
    "coin_id": "uniswap",
    "captured_at": "2026-04-02T07:40:35.838Z",
    "price_jpy": 532.5,
    "price_usd": 3.34,
    "change_24h": -7.613751680432429,
    "change_7d": 0,
    "market_cap_jpy": 337365695778.8843,
    "volume_24h_jpy": 38372972044.9131
  },
  {
    "coin_id": "usd-coin",
    "captured_at": "2026-04-02T07:40:35.838Z",
    "price_jpy": 159.66,
    "price_usd": 1,
    "change_24h": 0.8113167927020011,
    "change_7d": 0,
    "market_cap_jpy": 12324241394326.068,
    "volume_24h_jpy": 2167273033733.903
  },
  {
    "coin_id": "wrapped-bitcoin",
    "captured_at": "2026-04-02T07:40:35.838Z",
    "price_jpy": 10651112,
    "price_usd": 66714,
    "change_24h": -2.288793199512046,
    "change_7d": 0,
    "market_cap_jpy": 1268669985383.8171,
    "volume_24h_jpy": 36143919807.53063
  }
]