[
  {
    "coin_id": "avalanche-2",
    "captured_at": "2026-04-21T06:16:40.733Z",
    "price_jpy": 1486.22,
    "price_usd": 9.35,
    "change_24h": 3.1157993876650742,
    "change_7d": 0,
    "market_cap_jpy": 641765322902.6924,
    "volume_24h_jpy": 52354679536.50647
  },
  {
    "coin_id": "binancecoin",
    "captured_at": "2026-04-21T06:16:40.733Z",
    "price_jpy": 100197,
    "price_usd": 630.64,
    "change_24h": 1.715024686722227,
    "change_7d": 0,
    "market_cap_jpy": 13509402317557.045,
    "volume_24h_jpy": 159492635605.64844
  },
  {
    "coin_id": "bitcoin",
    "captured_at": "2026-04-21T06:16:40.733Z",
    "price_jpy": 12043863,
    "price_usd": 75804,
    "change_24h": 1.900440909601694,
    "change_7d": 0,
    "market_cap_jpy": 241075432317719.84,
    "volume_24h_jpy": 7300106739949.424
  },
  {
    "coin_id": "cardano",
    "captured_at": "2026-04-21T06:16:40.733Z",
    "price_jpy": 39.56,
    "price_usd": 0.249007,
    "change_24h": 1.8561364331522376,
    "change_7d": 0,
    "market_cap_jpy": 1462552658066.334,
    "volume_24h_jpy": 71626014939.4783
  },
  {
    "coin_id": "chainlink",
    "captured_at": "2026-04-21T06:16:40.733Z",
    "price_jpy": 1483.69,
    "price_usd": 9.34,
    "change_24h": 2.0216742930620963,
    "change_7d": 0,
    "market_cap_jpy": 1079021051534.5408,
    "volume_24h_jpy": 51274066326.76926
  },
  {
    "coin_id": "dogecoin",
    "captured_at": "2026-04-21T06:16:40.733Z",
    "price_jpy": 15.16,
    "price_usd": 0.095394,
    "change_24h": 1.4569027787535072,
    "change_7d": 0,
    "market_cap_jpy": 2332132204170.963,
    "volume_24h_jpy": 201618186016.92697
  },
  {
    "coin_id": "ethereum",
    "captured_at": "2026-04-21T06:16:40.733Z",
    "price_jpy": 367266,
    "price_usd": 2311.58,
    "change_24h": 1.6951828420180677,
    "change_7d": 0,
    "market_cap_jpy": 44334308279663.79,
    "volume_24h_jpy": 3328518589727.023
  },
  {
    "coin_id": "litecoin",
    "captured_at": "2026-04-21T06:16:40.733Z",
    "price_jpy": 8735.21,
    "price_usd": 54.98,
    "change_24h": 0.5476843956556032,
    "change_7d": 0,
    "market_cap_jpy": 673469366839.6582,
    "volume_24h_jpy": 47975555048.74962
  },
  {
    "coin_id": "matic-network",
    "captured_at": "2026-04-21T06:16:40.733Z",
    "price_jpy": 0,
    "price_usd": 0,
    "change_24h": 0,
    "change_7d": 0,
    "market_cap_jpy": 0,
    "volume_24h_jpy": 0
  },
  {
    "coin_id": "near",
    "captured_at": "2026-04-21T06:16:40.733Z",
    "price_jpy": 216.78,
    "price_usd": 1.36,
    "change_24h": 1.59640292180988,
    "change_7d": 0,
    "market_cap_jpy": 280729240302.3585,
    "volume_24h_jpy": 27582891679.797325
  },
  {
    "coin_id": "polkadot",
    "captured_at": "2026-04-21T06:16:40.733Z",
    "price_jpy": 202.96,
    "price_usd": 1.28,
    "change_24h": 1.8132468897312264,
    "change_7d": 0,
    "market_cap_jpy": 341364058811.00165,
    "volume_24h_jpy": 29717172289.027927
  },
  {
    "coin_id": "ripple",
    "captured_at": "2026-04-21T06:16:40.733Z",
    "price_jpy": 227.14,
    "price_usd": 1.43,
    "change_24h": 1.8141466021239605,
    "change_7d": 0,
    "market_cap_jpy": 13994562474961.977,
    "volume_24h_jpy": 413351024178.49603
  },
  {
    "coin_id": "shiba-inu",
    "captured_at": "2026-04-21T06:16:40.733Z",
    "price_jpy": 0.00095803,
    "price_usd": 0.00000603,
    "change_24h": 1.3907195750315817,
    "change_7d": 0,
    "market_cap_jpy": 564778507304.4017,
    "volume_24h_jpy": 14661705535.97566
  },
  {
    "coin_id": "solana",
    "captured_at": "2026-04-21T06:16:40.733Z",
    "price_jpy": 13595.3,
    "price_usd": 85.57,
    "change_24h": 1.847672854754755,
    "change_7d": 0,
    "market_cap_jpy": 7828201693786.596,
    "volume_24h_jpy": 554553736055.2205
  },
  {
    "coin_id": "staked-ether",
    "captured_at": "2026-04-21T06:16:40.733Z",
    "price_jpy": 364350,
    "price_usd": 2293.22,
    "change_24h": 1.342487768692327,
    "change_7d": 0,
    "market_cap_jpy": 3428182666697.8096,
    "volume_24h_jpy": 39327298793.66761
  },
  {
    "coin_id": "tether",
    "captured_at": "2026-04-21T06:16:40.733Z",
    "price_jpy": 158.92,
    "price_usd": 1,
    "change_24h": -0.03357563242763544,
    "change_7d": 0,
    "market_cap_jpy": 29866752237754.152,
    "volume_24h_jpy": 11224185513428.727
  },
  {
    "coin_id": "tron",
    "captured_at": "2026-04-21T06:16:40.733Z",
    "price_jpy": 52.22,
    "price_usd": 0.328671,
    "change_24h": -0.9205508357210043,
    "change_7d": 0,
    "market_cap_jpy": 4948971072442.287,
    "volume_24h_jpy": 87773184433.97763
  },
  {
    "coin_id": "uniswap",
    "captured_at": "2026-04-21T06:16:40.733Z",
    "price_jpy": 516.63,
    "price_usd": 3.25,
    "change_24h": -0.10072776592426907,
    "change_7d": 0,
    "market_cap_jpy": 327476660341.78595,
    "volume_24h_jpy": 31009539086.415512
  },
  {
    "coin_id": "usd-coin",
    "captured_at": "2026-04-21T06:16:40.733Z",
    "price_jpy": 158.85,
    "price_usd": 0.999788,
    "change_24h": -0.030977893424178782,
    "change_7d": 0,
    "market_cap_jpy": 12441323868948.375,
    "volume_24h_jpy": 2798266081075.095
  },
  {
    "coin_id": "wrapped-bitcoin",
    "captured_at": "2026-04-21T06:16:40.733Z",
    "price_jpy": 12028400,
    "price_usd": 75707,
    "change_24h": 2.2186905926359706,
    "change_7d": 0,
    "market_cap_jpy": 1425646144631.3003,
    "volume_24h_jpy": 31910513604.738384
  }
]