[
  {
    "coin_id": "avalanche-2",
    "captured_at": "2026-03-24T14:00:45.645Z",
    "price_jpy": 1500.57,
    "price_usd": 9.45,
    "change_24h": -1.3369065714282358,
    "change_7d": 0,
    "market_cap_jpy": 648062837485.7488,
    "volume_24h_jpy": 45123726150.80058
  },
  {
    "coin_id": "binancecoin",
    "captured_at": "2026-03-24T14:00:45.645Z",
    "price_jpy": 100366,
    "price_usd": 632,
    "change_24h": -2.2284431492923247,
    "change_7d": 0,
    "market_cap_jpy": 13684374403723.19,
    "volume_24h_jpy": 201465030211.62778
  },
  {
    "coin_id": "bitcoin",
    "captured_at": "2026-03-24T14:00:45.645Z",
    "price_jpy": 11127787,
    "price_usd": 70071,
    "change_24h": -1.9076934821954592,
    "change_7d": 0,
    "market_cap_jpy": 222539333598726.4,
    "volume_24h_jpy": 6125415653806.781
  },
  {
    "coin_id": "cardano",
    "captured_at": "2026-03-24T14:00:45.645Z",
    "price_jpy": 41.46,
    "price_usd": 0.261067,
    "change_24h": -0.6836366195173065,
    "change_7d": 0,
    "market_cap_jpy": 1528011812983.9585,
    "volume_24h_jpy": 71300370231.35072
  },
  {
    "coin_id": "chainlink",
    "captured_at": "2026-03-24T14:00:45.645Z",
    "price_jpy": 1447.74,
    "price_usd": 9.12,
    "change_24h": -0.2869702887791499,
    "change_7d": 0,
    "market_cap_jpy": 1025372620525.233,
    "volume_24h_jpy": 73022227769.41052
  },
  {
    "coin_id": "dogecoin",
    "captured_at": "2026-03-24T14:00:45.645Z",
    "price_jpy": 14.87,
    "price_usd": 0.09365,
    "change_24h": -0.32078149916040544,
    "change_7d": 0,
    "market_cap_jpy": 2284108163743.3506,
    "volume_24h_jpy": 183385174261.39243
  },
  {
    "coin_id": "ethereum",
    "captured_at": "2026-03-24T14:00:45.645Z",
    "price_jpy": 339559,
    "price_usd": 2138.18,
    "change_24h": -2.011554028500094,
    "change_7d": 0,
    "market_cap_jpy": 40968191033766.89,
    "volume_24h_jpy": 3052922458290.0903
  },
  {
    "coin_id": "litecoin",
    "captured_at": "2026-03-24T14:00:45.645Z",
    "price_jpy": 8810.08,
    "price_usd": 55.48,
    "change_24h": -0.32099238930553486,
    "change_7d": 0,
    "market_cap_jpy": 678407163466.6034,
    "volume_24h_jpy": 52570141002.184784
  },
  {
    "coin_id": "matic-network",
    "captured_at": "2026-03-24T14:00:45.645Z",
    "price_jpy": 0,
    "price_usd": 0,
    "change_24h": 0,
    "change_7d": 0,
    "market_cap_jpy": 0,
    "volume_24h_jpy": 0
  },
  {
    "coin_id": "near",
    "captured_at": "2026-03-24T14:00:45.645Z",
    "price_jpy": 205.26,
    "price_usd": 1.29,
    "change_24h": -1.36839008835099,
    "change_7d": 0,
    "market_cap_jpy": 265069398805.08737,
    "volume_24h_jpy": 27945042013.403885
  },
  {
    "coin_id": "polkadot",
    "captured_at": "2026-03-24T14:00:45.645Z",
    "price_jpy": 220.58,
    "price_usd": 1.39,
    "change_24h": -5.899313172798765,
    "change_7d": 0,
    "market_cap_jpy": 369769427921.8759,
    "volume_24h_jpy": 32370167901.59922
  },
  {
    "coin_id": "ripple",
    "captured_at": "2026-03-24T14:00:45.645Z",
    "price_jpy": 222.7,
    "price_usd": 1.4,
    "change_24h": -2.4367527035281804,
    "change_7d": 0,
    "market_cap_jpy": 13666213699892.246,
    "volume_24h_jpy": 401221473513.9762
  },
  {
    "coin_id": "shiba-inu",
    "captured_at": "2026-03-24T14:00:45.645Z",
    "price_jpy": 0.00096946,
    "price_usd": 0.0000061,
    "change_24h": 0.5205465735761794,
    "change_7d": 0,
    "market_cap_jpy": 571388578292.062,
    "volume_24h_jpy": 26291780364.47668
  },
  {
    "coin_id": "solana",
    "captured_at": "2026-03-24T14:00:45.645Z",
    "price_jpy": 14256.01,
    "price_usd": 89.77,
    "change_24h": -1.3255506012968579,
    "change_7d": 0,
    "market_cap_jpy": 8158129739694.782,
    "volume_24h_jpy": 681616721139.8204
  },
  {
    "coin_id": "staked-ether",
    "captured_at": "2026-03-24T14:00:45.645Z",
    "price_jpy": 339550,
    "price_usd": 2138.12,
    "change_24h": -2.0728432645609045,
    "change_7d": 0,
    "market_cap_jpy": 3115371498254.429,
    "volume_24h_jpy": 2251415086.915607
  },
  {
    "coin_id": "tether",
    "captured_at": "2026-03-24T14:00:45.645Z",
    "price_jpy": 158.78,
    "price_usd": 0.999805,
    "change_24h": 0.188607304362377,
    "change_7d": 0,
    "market_cap_jpy": 29250346093158.43,
    "volume_24h_jpy": 10631607431397.43
  },
  {
    "coin_id": "tron",
    "captured_at": "2026-03-24T14:00:45.645Z",
    "price_jpy": 49.23,
    "price_usd": 0.310026,
    "change_24h": 0.06935063229500363,
    "change_7d": 0,
    "market_cap_jpy": 4666202121513.58,
    "volume_24h_jpy": 86871682547.39526
  },
  {
    "coin_id": "uniswap",
    "captured_at": "2026-03-24T14:00:45.645Z",
    "price_jpy": 566.26,
    "price_usd": 3.56,
    "change_24h": -0.9496403408322055,
    "change_7d": 0,
    "market_cap_jpy": 358760079365.72955,
    "volume_24h_jpy": 28787948721.54194
  },
  {
    "coin_id": "usd-coin",
    "captured_at": "2026-03-24T14:00:45.645Z",
    "price_jpy": 158.83,
    "price_usd": 0.999927,
    "change_24h": 0.24023343025600608,
    "change_7d": 0,
    "market_cap_jpy": 12493757808752.771,
    "volume_24h_jpy": 1574773678376.7078
  },
  {
    "coin_id": "wrapped-bitcoin",
    "captured_at": "2026-03-24T14:00:45.645Z",
    "price_jpy": 11109103,
    "price_usd": 69953,
    "change_24h": -1.828967994669211,
    "change_7d": 0,
    "market_cap_jpy": 1324056384237.5298,
    "volume_24h_jpy": 21563937664.380913
  }
]